MANIFEST.in
README.rst
setup.py
backend/__init__.py
backend/admin.py
backend/api.py
backend/asgi.py
backend/decorators.py
backend/filters.py
backend/forms.py
backend/models.py
backend/settings.py
backend/urls.py
backend/views.py
backend/wsgi.py
backend/migrations/0001_initial.py
backend/migrations/0002_auto_20200731_2002.py
backend/migrations/__init__.py
backend/static_built/__init__.py
backend/static_built/assets/__init__.py
backend/static_built/assets/logo.png
backend/static_built/assets/logo_with_bg.jpg
backend/static_built/assets/atraccion-dinero-e-ingresos/6573.jpg
backend/static_built/assets/atraccion-dinero-e-ingresos/__init__.py
backend/static_built/assets/stock-exchange-data-illustration/4027811.jpg
backend/static_built/assets/stock-exchange-data-illustration/__init__.py
backend/static_built/css/__init__.py
backend/static_built/css/styles.css
backend/templates/__init__.py
backend/templates/base.html
backend/templates/landing_base.html
backend/templates/fourohfour/__init__.py
backend/templates/fourohfour/fourohfour.html
backend/templates/home/__init__.py
backend/templates/home/index.html
backend/templates/home/login.html
backend/templates/home/product_analytics.html
backend/templates/home/product_info.html
backend/templates/home/register.html
backend/templates/home/test.html
backend/templates/product_pages/__init__.py
backend/templates/product_pages/errorlisting.html
backend/templates/product_pages/index.html
backend/templates/product_pages/product_analytics.html
backend/templates/product_pages/product_info.html
backend/templates/product_pages/products_analytics.html
backend/tests/__init__.py
backend/tests/test_history.py
backend/tests/test_models.py
backend/tests/test_rust.py
backend/tests/test_urls.py
backend/tests/test_views.py
productiongraph.egg-info/PKG-INFO
productiongraph.egg-info/SOURCES.txt
productiongraph.egg-info/dependency_links.txt
productiongraph.egg-info/entry_points.txt
productiongraph.egg-info/requires.txt
productiongraph.egg-info/top_level.txt
scripts/__init__.py
scripts/init.py
scripts/migrate_and_run.py
scripts/run.py
scripts/test.py
static_built/__init__.py
static_built/assets/__init__.py
static_built/assets/logo.png
static_built/assets/logo_with_bg.jpg
