Metadata-Version: 1.0
Name: productiongraph
Version: 0.2.0
Summary: Web interface for calculating prices
Home-page: UNKNOWN
Author: Cameron, Aaron, Osiris, Benjamin, Matt
Author-email: cameron.g.rodgers@gmail.com
License: UNKNOWN
Platform: UNKNOWN
